main.py
pancakeswap_poolspy_mcp-0.1.0.dist-info/licenses/LICENSE
pancakeswap_poolspy_mcp-0.1.0.dist-info/METADATA
pancakeswap_poolspy_mcp-0.1.0.dist-info/WHEEL
pancakeswap_poolspy_mcp-0.1.0.dist-info/top_level.txt
pancakeswap_poolspy_mcp-0.1.0.dist-info/RECORD
